snaplogic/__init__.py
snaplogic/jupyter.py
snaplogic/tool.py
snaplogic/assets/load-script.html
snaplogic/assets/login.html
snaplogic/assets/paste-info.html
snaplogic/assets/render-main-menu.html
snaplogic/assets/save-script.html
snaplogic/assets/show-error-message.html
snaplogic/assets/show-preview-data.html
snaplogic/assets/show-status.html
snaplogic/assets/snap-info-alert.html
snaplogic/assets/snaplogic_logo.png
snaplogic-0.0.5.dist-info/LICENSE
snaplogic-0.0.5.dist-info/METADATA
snaplogic-0.0.5.dist-info/WHEEL
snaplogic-0.0.5.dist-info/top_level.txt
snaplogic-0.0.5.dist-info/RECORD
